PySIP/__init__.py
PySIP/audio_stream.py
PySIP/call_handler.py
PySIP/exceptions.py
PySIP/filters.py
PySIP/jitter_buffer.py
PySIP/rtp_handler.py
PySIP/sip_account.py
PySIP/sip_call.py
PySIP/sip_client.py
PySIP/sip_core.py
PySIP/udp_handler.py
PySIP/amd/__init__.py
PySIP/amd/amd.py
PySIP/amd/silence_detection.py
PySIP/amd/tone_detection.py
PySIP/codecs/__init__.py
PySIP/codecs/base.py
PySIP/codecs/codec_info.py
PySIP/codecs/g711.py
PySIP/utils/__init__.py
PySIP/utils/async_utils.py
PySIP/utils/inband_dtmf.py
PySIP/utils/logger.py
PySIPio-1.8.0.dist-info/LICENSE
PySIPio-1.8.0.dist-info/METADATA
PySIPio-1.8.0.dist-info/WHEEL
PySIPio-1.8.0.dist-info/top_level.txt
PySIPio-1.8.0.dist-info/RECORD
