Metadata-Version: 2.1
Name: PySIPio
Version: 1.8.0
Summary: Python SIP Library for Custom VoIP Solutions
Author-email: Moha Abdi <mohaa6052@gmail.com>
License: MIT
Project-URL: Homepage, https://github.com/moha-abdi/PySIP
Project-URL: Bug Tracker, https://github.com/moha-abdi/PySIP/issues
Keywords: SIP,VoIP,Session Initiation Protocol,Voice over IP,telephony,communication,UDP,async,asynchronous,call handling,PBX,IVR,interactive voice response
Classifier: Programming Language :: Python :: 3
Classifier: Programming Language :: Python :: 3.8
Classifier: License :: OSI Approved :: MIT License
Classifier: Operating System :: OS Independent
Classifier: Topic :: Communications :: Internet Phone
Classifier: Topic :: Software Development :: Libraries :: Python Modules
Requires-Python: >=3.8
License-File: LICENSE
Requires-Dist: pydub>=0.25.1
Requires-Dist: requests>=2.25.1
Requires-Dist: edge-tts>=5.0.0
Requires-Dist: python-dotenv>=0.19.0
